pyproject.toml
cellwell/__init__.py
cellwell.egg-info/PKG-INFO
cellwell.egg-info/SOURCES.txt
cellwell.egg-info/dependency_links.txt
cellwell.egg-info/requires.txt
cellwell.egg-info/top_level.txt