Metadata-Version: 2.4
Name: cellwell
Version: 0.1.0
Summary: User interface for deformability cytometry (DC)
Author: Paul Müller
Maintainer-email: Paul Müller <dev@craban.de>
License-Expression: GPL-3.0-or-later
Keywords: RT-DC,DC,deformability,cytometry
Classifier: Operating System :: OS Independent
Classifier: Programming Language :: Python :: 3
Classifier: Intended Audience :: Science/Research
Requires-Python: <4,>=3.9
Requires-Dist: dclab[dcor,export,http,s3]>=0.64.0
Requires-Dist: h5py>=2.8.0
Requires-Dist: numpy>=1.21
Requires-Dist: pygments
Requires-Dist: pyqt6
Requires-Dist: pyqtgraph==0.13.6
Requires-Dist: requests>=2.31.0
Requires-Dist: scipy>=1.10.0
